README.md
setup.py
imgload/Imgloader.py
imgload/__init__.py
imgload.egg-info/PKG-INFO
imgload.egg-info/SOURCES.txt
imgload.egg-info/dependency_links.txt
imgload.egg-info/requires.txt
imgload.egg-info/top_level.txt
imgload/img_hosts/Fastpic.py
imgload/img_hosts/ImageHost.py
imgload/img_hosts/Imagebam.py
imgload/img_hosts/Imagevenue.py
imgload/img_hosts/Imgur.py
imgload/img_hosts/Postimg.py
imgload/img_hosts/__init__.py