Metadata-Version: 2.1
Name: imgload
Version: 0.2.1
Summary: An image downloading library
Home-page: https://github.com/frenos/imgload
Author: frenos
License: UNKNOWN
Platform: UNKNOWN
Classifier: Programming Language :: Python :: 3
Classifier: Programming Language :: Python :: 3.7
Classifier: License :: OSI Approved :: GNU General Public License v3 (GPLv3)
Classifier: Operating System :: OS Independent
Requires-Python: >=3.7
